{
    "1101": "7.80",
    "1102": "7.98",
    "1103": "9.24",
    "1104": "17.18",
    "1108": "16.03",
    "1109": "14.87",
    "1110": "14.75",
    "1201": "16.87",
    "1203": "145.00",
    "1210": "10.41",
    "1213": "95.75",
    "1215": "6.50",
    "1216": "11.80",
    "1217": "-",
    "1218": "9.25",
    "1219": "8.11",
    "1220": "74.14",
    "1225": "4.04",
    "1227": "12.18",
    "1229": "6.54",
    "1231": "12.58",
    "1232": "5.99",
    "1233": "16.42",
    "1234": "39.81",
    "1235": "12.70",
    "1236": "6.89",
    "1301": "5.77",
    "1303": "6.67",
    "1304": "4.74",
    "1305": "5.65",
    "1307": "8.92",
    "1308": "4.11",
    "1309": "6.52",
    "1310": "16.17",
    "1312": "5.38",
    "1313": "5.34",
    "1314": "13.39",
    "1315": "11.14",
    "1316": "11.76",
    "1319": "8.22",
    "1321": "-",
    "1323": "7.75",
    "1324": "-",
    "1325": "6.77",
    "1326": "7.02",
    "1402": "10.93",
    "1409": "30.53",
    "1410": "-",
    "1413": "66.67",
    "1414": "-",
    "1416": "-",
    "1417": "12.79",
    "1418": "-",
    "1419": "-",
    "1423": "35.77",
    "1432": "0.61",
    "1434": "5.33",
    "1435": "-",
    "1436": "-",
    "1437": "15.57",
    "1438": "-",
    "1439": "52.38",
    "1440": "14.00",
    "1441": "-",
    "1442": "12.36",
    "1443": "-",
    "1444": "6.82",
    "1445": "-",
    "1446": "32.35",
    "1447": "-",
    "1449": "-",
    "1451": "6.85",
    "1452": "25.86",
    "1453": "1.02",
    "1454": "38.46",
    "1455": "10.36",
    "1456": "1.74",
    "1457": "20.21",
    "1459": "-",
    "1460": "-",
    "1463": "-",
    "1464": "-",
    "1465": "9.28",
    "1466": "6.76",
    "1467": "-",
    "1468": "-",
    "1469": "-",
    "1470": "45.94",
    "1471": "-",
    "1472": "-",
    "1473": "7.44",
    "1474": "27.35",
    "1475": "-",
    "1476": "8.60",
    "1477": "5.33",
    "1503": "14.15",
    "1504": "8.70",
    "1506": "-",
    "1507": "7.90",
    "1512": "14.52",
    "1513": "9.25",
    "1514": "50.25",
    "1515": "-",
    "1516": "-",
    "1517": "11.26",
    "1519": "10.91",
    "1521": "7.85",
    "1522": "7.97",
    "1523": "9.50",
    "1524": "35.45",
    "1525": "7.24",
    "1526": "12.93",
    "1527": "-",
    "1528": "10.00",
    "1529": "-",
    "1530": "5.58",
    "1531": "11.14",
    "1532": "8.88",
    "1533": "11.95",
    "1535": "13.51",
    "1536": "14.85",
    "1537": "5.71",
    "1538": "11.95",
    "1539": "40.91",
    "1540": "5.49",
    "1541": "22.13",
    "1560": "7.63",
    "1583": "6.78",
    "1603": "8.38",
    "1604": "14.42",
    "1605": "67.62",
    "1608": "10.46",
    "1609": "11.63",
    "1611": "8.91",
    "1612": "10.61",
    "1613": "-",
    "1614": "18.64",
    "1615": "4.52",
    "1616": "34.53",
    "1617": "9.02",
    "1618": "31.45",
    "1701": "14.13",
    "1702": "-",
    "1704": "10.08",
    "1707": "12.70",
    "1708": "11.30",
    "1709": "9.23",
    "1710": "5.28",
    "1711": "31.04",
    "1712": "9.27",
    "1713": "20.57",
    "1714": "14.60",
    "1715": "29.88",
    "1716": "12.87",
    "1717": "7.37",
    "1718": "6.04",
    "1720": "11.11",
    "1721": "59.50",
    "1722": "14.49",
    "1723": "9.77",
    "1724": "9.68",
    "1725": "7.11",
    "1726": "8.70",
    "1727": "12.20",
    "1729": "35.84",
    "1730": "12.65",
    "1731": "16.46",
    "1732": "17.31",
    "1733": "10.78",
    "1734": "33.81",
    "1735": "10.53",
    "1736": "31.22",
    "1737": "-",
    "1802": "13.03",
    "1805": "19.21",
    "1806": "4.55",
    "1808": "10.61",
    "1809": "12.65",
    "1810": "-",
    "1902": "3.38",
    "1903": "-",
    "1904": "11.04",
    "1905": "7.84",
    "1906": "9.34",
    "1907": "8.42",
    "1909": "13.24",
    "2002": "7.22",
    "2006": "5.09",
    "2007": "-",
    "2008": "2.64",
    "2009": "7.17",
    "2010": "6.57",
    "2012": "8.67",
    "2013": "8.24",
    "2014": "4.30",
    "2015": "5.08",
    "2017": "-",
    "2020": "99.47",
    "2022": "6.42",
    "2023": "8.42",
    "2024": "5.89",
    "2025": "-",
    "2027": "8.25",
    "2028": "4.07",
    "2029": "8.42",
    "2030": "40.77",
    "2031": "3.78",
    "2032": "-",
    "2033": "27.83",
    "2034": "43.75",
    "2059": "13.72",
    "2062": "19.94",
    "2101": "68.29",
    "2102": "10.25",
    "2103": "6.60",
    "2104": "7.66",
    "2105": "10.58",
    "2106": "25.86",
    "2107": "10.18",
    "2108": "7.42",
    "2109": "-",
    "2201": "13.05",
    "2204": "34.38",
    "2206": "7.74",
    "2207": "11.84",
    "2227": "7.56",
    "2301": "9.29",
    "2302": "-",
    "2303": "10.79",
    "2305": "284.00",
    "2308": "13.08",
    "2311": "7.35",
    "2312": "10.48",
    "2313": "91.38",
    "2314": "13.07",
    "2315": "5.61",
    "2316": "-",
    "2317": "11.16",
    "2321": "-",
    "2323": "-",
    "2324": "6.45",
    "2325": "8.22",
    "2327": "30.50",
    "2328": "19.00",
    "2329": "-",
    "2330": "11.27",
    "2331": "8.37",
    "2332": "7.39",
    "2337": "6.25",
    "2338": "6.24",
    "2340": "11.18",
    "2341": "-",
    "2342": "-",
    "2344": "-",
    "2345": "-",
    "2347": "15.67",
    "2348": "35.00",
    "2349": "-",
    "2350": "6.33",
    "2351": "6.90",
    "2352": "2.93",
    "2353": "12.55",
    "2354": "11.02",
    "2355": "7.25",
    "2356": "7.78",
    "2357": "9.79",
    "2358": "52.38",
    "2359": "4.08",
    "2360": "7.85",
    "2361": "-",
    "2362": "18.92",
    "2363": "-",
    "2364": "-",
    "2365": "7.78",
    "2367": "7.24",
    "2368": "5.18",
    "2369": "8.18",
    "2371": "9.76",
    "2373": "14.65",
    "2374": "6.27",
    "2375": "4.51",
    "2376": "7.22",
    "2377": "5.38",
    "2379": "31.67",
    "2380": "8.79",
    "2381": "-",
    "2382": "7.21",
    "2383": "5.85",
    "2384": "31.38",
    "2385": "9.75",
    "2387": "10.04",
    "2388": "-",
    "2390": "-",
    "2391": "10.68",
    "2392": "11.56",
    "2393": "10.50",
    "2395": "10.78",
    "2397": "10.89",
    "2399": "7.06",
    "2401": "9.78",
    "2402": "13.19",
    "2403": "6.70",
    "2404": "6.70",
    "2405": "21.30",
    "2406": "-",
    "2408": "-",
    "2409": "2.94",
    "2411": "17.97",
    "2412": "15.11",
    "2413": "-",
    "2414": "6.78",
    "2415": "22.66",
    "2417": "6.11",
    "2419": "6.97",
    "2420": "6.78",
    "2421": "28.68",
    "2423": "7.29",
    "2424": "-",
    "2425": "-",
    "2426": "18.94",
    "2427": "-",
    "2428": "11.47",
    "2429": "-",
    "2430": "2.88",
    "2431": "-",
    "2433": "5.03",
    "2434": "25.25",
    "2436": "17.24",
    "2437": "5.86",
    "2438": "-",
    "2439": "10.13",
    "2440": "14.00",
    "2441": "5.71",
    "2442": "-",
    "2443": "-",
    "2444": "58.92",
    "2446": "8.21",
    "2448": "17.31",
    "2449": "6.02",
    "2450": "7.42",
    "2451": "9.49",
    "2452": "10.89",
    "2453": "-",
    "2454": "12.78",
    "2455": "33.52",
    "2456": "7.78",
    "2457": "7.93",
    "2458": "17.20",
    "2459": "5.28",
    "2460": "7.15",
    "2461": "5.31",
    "2462": "12.40",
    "2463": "11.09",
    "2464": "5.86",
    "2465": "-",
    "2466": "121.38",
    "2467": "6.68",
    "2468": "3.99",
    "2471": "-",
    "2472": "-",
    "2473": "7.66",
    "2474": "8.41",
    "2475": "2.80",
    "2476": "7.41",
    "2477": "12.05",
    "2478": "13.50",
    "2480": "8.88",
    "2481": "16.11",
    "2482": "18.15",
    "2483": "26.71",
    "2484": "9.79",
    "2485": "6.96",
    "2486": "7.96",
    "2488": "6.47",
    "2489": "5.34",
    "2492": "14.03",
    "2493": "11.52",
    "2494": "-",
    "2495": "5.66",
    "2496": "-",
    "2497": "48.89",
    "2498": "11.90",
    "2499": "-",
    "2501": "18.18",
    "2504": "12.43",
    "2505": "5.03",
    "2506": "9.06",
    "2509": "4.09",
    "2511": "-",
    "2514": "-",
    "2515": "17.22",
    "2516": "9.32",
    "2520": "5.45",
    "2524": "6.15",
    "2526": "12.65",
    "2527": "46.33",
    "2528": "-",
    "2530": "-",
    "2534": "2.68",
    "2535": "9.15",
    "2536": "2.66",
    "2537": "-",
    "2538": "5.39",
    "2539": "-",
    "2540": "10.47",
    "2542": "4.57",
    "2543": "10.14",
    "2545": "5.74",
    "2546": "7.82",
    "2547": "9.65",
    "2548": "3.34",
    "2601": "5.69",
    "2603": "4.57",
    "2605": "6.05",
    "2606": "3.65",
    "2607": "18.55",
    "2608": "-",
    "2609": "4.50",
    "2610": "-",
    "2611": "50.74",
    "2612": "5.70",
    "2613": "6.41",
    "2614": "19.78",
    "2615": "5.42",
    "2616": "7.99",
    "2617": "7.58",
    "2618": "-",
    "2701": "20.10",
    "2702": "57.67",
    "2704": "34.31",
    "2705": "-",
    "2706": "16.20",
    "2707": "28.76",
    "2801": "12.04",
    "2809": "21.97",
    "2812": "7.49",
    "2816": "-",
    "2820": "10.13",
    "2823": "14.67",
    "2832": "8.33",
    "2833": "-",
    "2834": "10.79",
    "2836": "-",
    "2837": "-",
    "2838": "-",
    "2841": "3.94",
    "2845": "-",
    "2847": "-",
    "2849": "-",
    "2850": "6.72",
    "2851": "5.75",
    "2852": "48.53",
    "2854": "11.01",
    "2855": "11.07",
    "2856": "-",
    "2880": "11.09",
    "2881": "12.93",
    "2882": "53.94",
    "2883": "-",
    "2884": "11.13",
    "2885": "23.87",
    "2886": "15.49",
    "2887": "5.24",
    "2888": "-",
    "2889": "10.32",
    "2890": "-",
    "2891": "10.71",
    "2892": "8.92",
    "2901": "82.27",
    "2903": "33.39",
    "2904": "9.45",
    "2905": "-",
    "2906": "88.80",
    "2908": "16.54",
    "2910": "14.64",
    "2911": "15.77",
    "2912": "24.80",
    "2913": "-",
    "2915": "23.51",
    "3002": "8.33",
    "3003": "8.35",
    "3004": "-",
    "3005": "6.15",
    "3006": "9.92",
    "3008": "15.57",
    "3009": "2.44",
    "3010": "6.58",
    "3011": "-",
    "3013": "31.68",
    "3014": "10.82",
    "3015": "7.11",
    "3016": "88.68",
    "3017": "7.16",
    "3018": "-",
    "3019": "8.32",
    "3021": "6.29",
    "3022": "7.64",
    "3023": "5.16",
    "3024": "11.00",
    "3025": "14.06",
    "3026": "7.43",
    "3027": "6.49",
    "3028": "7.56",
    "3029": "15.59",
    "3030": "5.75",
    "3031": "11.29",
    "3032": "5.74",
    "3033": "7.77",
    "3034": "4.71",
    "3035": "11.38",
    "3036": "5.21",
    "3037": "5.62",
    "3038": "-",
    "3040": "5.74",
    "3041": "22.50",
    "3042": "10.42",
    "3043": "24.93",
    "3044": "7.08",
    "3045": "28.93",
    "3046": "5.15",
    "3047": "10.50",
    "3048": "6.49",
    "3050": "29.33",
    "3051": "-",
    "3052": "7.64",
    "3054": "25.14",
    "3055": "5.26",
    "3056": "-",
    "3057": "13.79",
    "3058": "-",
    "3059": "6.20",
    "3060": "9.02",
    "3061": "14.02",
    "3062": "18.14",
    "3063": "-",
    "3080": "5.28",
    "3090": "6.69",
    "3094": "13.15",
    "3130": "9.71",
    "3189": "5.88",
    "3231": "8.14",
    "3296": "6.75",
    "3305": "9.70",
    "3308": "9.44",
    "3311": "10.72",
    "3315": "4.80",
    "3356": "9.19",
    "3367": "5.93",
    "3376": "13.31",
    "3380": "8.14",
    "3383": "14.48",
    "3406": "-",
    "3419": "-",
    "3443": "28.91",
    "3450": "7.75",
    "3474": "-",
    "3481": "6.94",
    "3494": "15.12",
    "3501": "9.17",
    "3504": "12.38",
    "3514": "17.38",
    "3515": "6.90",
    "3518": "8.16",
    "3519": "14.69",
    "3532": "10.58",
    "3533": "7.17",
    "3534": "10.46",
    "3535": "7.59",
    "3536": "3.23",
    "3545": "15.64",
    "3557": "3.89",
    "3701": "-",
    "3702": "7.60",
    "4104": "8.36",
    "4106": "8.95",
    "4108": "-",
    "4119": "9.73",
    "4306": "8.11",
    "4414": "-",
    "4526": "5.99",
    "4532": "9.48",
    "4725": "4.14",
    "4904": "12.19",
    "4906": "12.26",
    "5203": "13.33",
    "5305": "6.26",
    "5388": "5.57",
    "5434": "6.01",
    "5469": "5.20",
    "5471": "8.73",
    "5484": "7.97",
    "5515": "7.48",
    "5522": "3.93",
    "5525": "4.13",
    "5531": "4.36",
    "5533": "2.81",
    "5534": "3.79",
    "5607": "17.37",
    "5608": "6.67",
    "5854": "9.84",
    "6005": "10.34",
    "6012": "-",
    "6112": "7.47",
    "6115": "7.71",
    "6116": "2.02",
    "6117": "12.09",
    "6119": "6.50",
    "6120": "-",
    "6128": "10.00",
    "6131": "9.50",
    "6133": "9.56",
    "6136": "4.95",
    "6139": "6.21",
    "6141": "5.78",
    "6142": "8.93",
    "6145": "-",
    "6153": "-",
    "6155": "9.85",
    "6165": "-",
    "6166": "6.22",
    "6168": "11.85",
    "6172": "-",
    "6176": "6.43",
    "6184": "11.44",
    "6189": "5.54",
    "6191": "5.37",
    "6192": "7.27",
    "6196": "7.69",
    "6197": "23.36",
    "6201": "6.74",
    "6202": "6.85",
    "6205": "5.09",
    "6206": "8.58",
    "6209": "10.26",
    "6213": "5.68",
    "6215": "8.17",
    "6216": "5.35",
    "6225": "15.18",
    "6235": "-",
    "6239": "6.74",
    "6255": "17.98",
    "6257": "6.15",
    "6269": "16.62",
    "6271": "9.60",
    "6277": "10.00",
    "6281": "7.93",
    "6282": "8.55",
    "6283": "7.64",
    "6285": "7.88",
    "6286": "13.15",
    "6289": "-",
    "6505": "10.01",
    "6605": "6.33",
    "8008": "8.68",
    "8016": "9.70",
    "8021": "5.73",
    "8033": "18.51",
    "8046": "7.60",
    "8070": "7.08",
    "8072": "11.00",
    "8078": "8.76",
    "8101": "-",
    "8105": "10.78",
    "8110": "5.24",
    "8112": "-",
    "8131": "6.58",
    "8163": "7.18",
    "8201": "10.22",
    "8249": "7.16",
    "8926": "15.44",
    "9902": "-",
    "9904": "7.34",
    "9905": "9.35",
    "9906": "7.69",
    "9907": "10.43",
    "9908": "21.56",
    "9910": "7.24",
    "9911": "7.42",
    "9912": "4.90",
    "9914": "8.53",
    "9917": "11.60",
    "9918": "17.26",
    "9919": "13.03",
    "9921": "12.16",
    "9922": "32.33",
    "9924": "110.00",
    "9925": "9.73",
    "9926": "9.42",
    "9927": "3.84",
    "9928": "-",
    "9929": "-",
    "9930": "8.32",
    "9931": "15.42",
    "9933": "8.17",
    "9934": "10.97",
    "9935": "21.32",
    "9937": "12.85",
    "9938": "9.83",
    "9939": "10.97",
    "9940": "9.63",
    "9941": "8.94",
    "9942": "7.14",
    "9943": "7.96",
    "9944": "1.38",
    "9945": "21.22",
    "9955": "13.11",
    "9958": "10.44"
}