{
    "1101": "7.49",
    "1102": "7.72",
    "1103": "8.38",
    "1104": "16.54",
    "1108": "15.11",
    "1109": "14.06",
    "1110": "13.87",
    "1201": "16.73",
    "1203": "141.25",
    "1210": "9.52",
    "1213": "91.13",
    "1215": "5.89",
    "1216": "11.94",
    "1217": "-",
    "1218": "7.87",
    "1219": "7.22",
    "1220": "67.14",
    "1225": "3.57",
    "1227": "7.80",
    "1229": "6.23",
    "1231": "12.08",
    "1232": "5.47",
    "1233": "16.36",
    "1234": "38.04",
    "1235": "12.38",
    "1236": "6.71",
    "1301": "5.69",
    "1303": "6.25",
    "1304": "4.30",
    "1305": "4.82",
    "1307": "8.62",
    "1308": "3.88",
    "1309": "5.97",
    "1310": "15.15",
    "1312": "4.79",
    "1313": "4.91",
    "1314": "11.78",
    "1315": "10.49",
    "1316": "11.09",
    "1319": "7.76",
    "1321": "-",
    "1323": "7.52",
    "1324": "-",
    "1325": "6.64",
    "1326": "6.65",
    "1402": "9.63",
    "1409": "25.79",
    "1410": "-",
    "1413": "59.00",
    "1414": "-",
    "1416": "-",
    "1417": "11.53",
    "1418": "-",
    "1419": "-",
    "1423": "32.23",
    "1432": "0.50",
    "1434": "4.91",
    "1435": "-",
    "1436": "-",
    "1437": "13.78",
    "1438": "-",
    "1439": "54.52",
    "1440": "12.57",
    "1441": "-",
    "1442": "12.36",
    "1443": "-",
    "1444": "6.26",
    "1445": "-",
    "1446": "31.05",
    "1447": "-",
    "1449": "-",
    "1451": "6.56",
    "1452": "23.41",
    "1453": "0.85",
    "1454": "36.38",
    "1455": "9.50",
    "1456": "1.55",
    "1457": "17.75",
    "1459": "-",
    "1460": "-",
    "1463": "-",
    "1464": "-",
    "1465": "9.20",
    "1466": "6.36",
    "1467": "-",
    "1468": "-",
    "1469": "-",
    "1470": "42.81",
    "1471": "-",
    "1472": "-",
    "1473": "6.77",
    "1474": "25.53",
    "1475": "-",
    "1476": "8.20",
    "1477": "5.44",
    "1503": "12.36",
    "1504": "7.91",
    "1506": "-",
    "1507": "7.62",
    "1512": "14.52",
    "1513": "8.37",
    "1514": "45.83",
    "1515": "-",
    "1516": "-",
    "1517": "10.89",
    "1519": "10.38",
    "1521": "7.58",
    "1522": "7.70",
    "1523": "9.38",
    "1524": "32.59",
    "1525": "6.78",
    "1526": "12.49",
    "1527": "-",
    "1528": "9.28",
    "1529": "-",
    "1530": "5.21",
    "1531": "10.48",
    "1532": "7.55",
    "1533": "11.20",
    "1535": "12.98",
    "1536": "14.31",
    "1537": "5.47",
    "1538": "11.90",
    "1539": "39.91",
    "1540": "5.23",
    "1541": "21.93",
    "1560": "7.18",
    "1583": "6.47",
    "1603": "7.54",
    "1604": "14.00",
    "1605": "64.38",
    "1608": "9.83",
    "1609": "10.98",
    "1611": "9.15",
    "1612": "10.61",
    "1613": "-",
    "1614": "16.56",
    "1615": "4.49",
    "1616": "30.94",
    "1617": "8.55",
    "1618": "30.77",
    "1701": "13.23",
    "1702": "-",
    "1704": "8.95",
    "1707": "11.95",
    "1708": "9.71",
    "1709": "9.18",
    "1710": "4.78",
    "1711": "28.44",
    "1712": "8.45",
    "1713": "20.14",
    "1714": "14.04",
    "1715": "28.69",
    "1716": "12.55",
    "1717": "7.14",
    "1718": "5.47",
    "1720": "10.78",
    "1721": "56.00",
    "1722": "10.62",
    "1723": "9.10",
    "1724": "9.72",
    "1725": "6.88",
    "1726": "8.33",
    "1727": "11.44",
    "1729": "36.03",
    "1730": "12.24",
    "1731": "17.08",
    "1732": "17.02",
    "1733": "10.66",
    "1734": "32.20",
    "1735": "10.51",
    "1736": "25.65",
    "1737": "-",
    "1802": "11.61",
    "1805": "15.54",
    "1806": "4.35",
    "1808": "10.09",
    "1809": "11.49",
    "1810": "-",
    "1902": "2.97",
    "1903": "-",
    "1904": "11.14",
    "1905": "7.09",
    "1906": "8.16",
    "1907": "7.92",
    "1909": "12.70",
    "2002": "6.55",
    "2006": "4.41",
    "2007": "-",
    "2008": "2.22",
    "2009": "6.40",
    "2010": "6.07",
    "2012": "8.56",
    "2013": "8.15",
    "2014": "4.14",
    "2015": "4.27",
    "2017": "-",
    "2020": "92.11",
    "2022": "5.67",
    "2023": "8.19",
    "2024": "5.11",
    "2025": "-",
    "2027": "7.80",
    "2028": "3.32",
    "2029": "8.23",
    "2030": "38.35",
    "2031": "3.48",
    "2032": "-",
    "2033": "32.78",
    "2034": "41.72",
    "2059": "11.91",
    "2062": "18.06",
    "2101": "59.00",
    "2102": "9.83",
    "2103": "5.74",
    "2104": "7.78",
    "2105": "9.89",
    "2106": "23.02",
    "2107": "9.91",
    "2108": "7.02",
    "2109": "-",
    "2201": "11.17",
    "2204": "35.31",
    "2206": "6.99",
    "2207": "11.40",
    "2227": "7.17",
    "2301": "8.24",
    "2302": "-",
    "2303": "10.22",
    "2305": "272.00",
    "2308": "12.01",
    "2311": "6.43",
    "2312": "9.58",
    "2313": "81.38",
    "2314": "12.03",
    "2315": "4.74",
    "2316": "-",
    "2317": "9.18",
    "2321": "-",
    "2323": "-",
    "2324": "6.27",
    "2325": "7.23",
    "2327": "28.09",
    "2328": "17.93",
    "2329": "-",
    "2330": "9.86",
    "2331": "8.04",
    "2332": "6.99",
    "2337": "6.29",
    "2338": "5.84",
    "2340": "10.28",
    "2341": "-",
    "2342": "-",
    "2344": "-",
    "2345": "-",
    "2347": "13.86",
    "2348": "33.57",
    "2349": "-",
    "2350": "6.50",
    "2351": "6.12",
    "2352": "2.51",
    "2353": "11.32",
    "2354": "9.67",
    "2355": "6.73",
    "2356": "6.99",
    "2357": "8.38",
    "2358": "47.88",
    "2359": "3.68",
    "2360": "6.80",
    "2361": "-",
    "2362": "16.72",
    "2363": "-",
    "2364": "-",
    "2365": "6.58",
    "2367": "6.16",
    "2368": "4.90",
    "2369": "7.72",
    "2371": "8.53",
    "2373": "14.72",
    "2374": "5.93",
    "2375": "3.99",
    "2376": "6.10",
    "2377": "4.91",
    "2379": "29.58",
    "2380": "7.93",
    "2381": "-",
    "2382": "6.28",
    "2383": "5.61",
    "2384": "29.25",
    "2385": "8.20",
    "2387": "9.61",
    "2388": "-",
    "2390": "-",
    "2391": "10.32",
    "2392": "11.48",
    "2393": "9.43",
    "2395": "9.76",
    "2397": "8.72",
    "2399": "7.63",
    "2401": "9.05",
    "2402": "13.46",
    "2403": "6.05",
    "2404": "6.44",
    "2405": "20.28",
    "2406": "-",
    "2408": "-",
    "2409": "2.70",
    "2411": "17.99",
    "2412": "14.99",
    "2413": "-",
    "2414": "6.14",
    "2415": "20.49",
    "2417": "5.28",
    "2419": "7.79",
    "2420": "6.96",
    "2421": "25.66",
    "2423": "7.31",
    "2424": "-",
    "2425": "-",
    "2426": "17.88",
    "2427": "-",
    "2428": "10.87",
    "2429": "-",
    "2430": "2.68",
    "2431": "-",
    "2433": "5.01",
    "2434": "26.53",
    "2436": "17.04",
    "2437": "6.09",
    "2438": "-",
    "2439": "8.72",
    "2440": "13.16",
    "2441": "5.21",
    "2442": "-",
    "2443": "-",
    "2444": "51.83",
    "2446": "7.45",
    "2448": "16.31",
    "2449": "5.27",
    "2450": "7.14",
    "2451": "8.77",
    "2452": "10.49",
    "2453": "-",
    "2454": "10.97",
    "2455": "31.69",
    "2456": "7.45",
    "2457": "7.44",
    "2458": "15.69",
    "2459": "5.02",
    "2460": "6.19",
    "2461": "4.65",
    "2462": "12.60",
    "2463": "11.00",
    "2464": "5.55",
    "2465": "-",
    "2466": "117.24",
    "2467": "6.12",
    "2468": "3.83",
    "2471": "-",
    "2472": "-",
    "2473": "7.21",
    "2474": "7.42",
    "2475": "2.46",
    "2476": "7.00",
    "2477": "11.59",
    "2478": "12.46",
    "2480": "8.20",
    "2481": "14.68",
    "2482": "18.21",
    "2483": "26.32",
    "2484": "8.90",
    "2485": "6.17",
    "2486": "7.49",
    "2488": "6.33",
    "2489": "4.82",
    "2492": "13.44",
    "2493": "9.99",
    "2494": "-",
    "2495": "5.22",
    "2496": "-",
    "2497": "46.67",
    "2498": "9.95",
    "2499": "-",
    "2501": "15.73",
    "2504": "10.52",
    "2505": "4.12",
    "2506": "7.84",
    "2509": "3.54",
    "2511": "-",
    "2514": "-",
    "2515": "16.19",
    "2516": "8.95",
    "2520": "4.69",
    "2524": "5.44",
    "2526": "10.99",
    "2527": "46.27",
    "2528": "-",
    "2530": "-",
    "2534": "2.23",
    "2535": "8.38",
    "2536": "2.19",
    "2537": "-",
    "2538": "6.08",
    "2539": "-",
    "2540": "10.47",
    "2542": "4.22",
    "2543": "9.86",
    "2545": "4.74",
    "2546": "7.89",
    "2547": "9.82",
    "2548": "3.00",
    "2601": "5.52",
    "2603": "4.32",
    "2605": "5.54",
    "2606": "3.45",
    "2607": "17.05",
    "2608": "-",
    "2609": "4.10",
    "2610": "-",
    "2611": "50.56",
    "2612": "5.15",
    "2613": "5.73",
    "2614": "17.91",
    "2615": "5.38",
    "2616": "7.09",
    "2617": "7.54",
    "2618": "-",
    "2701": "19.42",
    "2702": "48.67",
    "2704": "25.51",
    "2705": "-",
    "2706": "14.11",
    "2707": "21.61",
    "2801": "9.88",
    "2809": "17.45",
    "2812": "6.35",
    "2816": "-",
    "2820": "9.13",
    "2823": "13.75",
    "2832": "7.19",
    "2833": "-",
    "2834": "10.07",
    "2836": "-",
    "2837": "-",
    "2838": "-",
    "2841": "3.47",
    "2845": "-",
    "2847": "-",
    "2849": "-",
    "2850": "5.77",
    "2851": "5.65",
    "2852": "44.65",
    "2854": "9.59",
    "2855": "9.39",
    "2856": "-",
    "2880": "9.68",
    "2881": "10.69",
    "2882": "45.56",
    "2883": "-",
    "2884": "9.81",
    "2885": "22.32",
    "2886": "13.15",
    "2887": "5.06",
    "2888": "-",
    "2889": "10.26",
    "2890": "-",
    "2891": "8.86",
    "2892": "7.51",
    "2901": "80.00",
    "2903": "30.65",
    "2904": "9.22",
    "2905": "-",
    "2906": "73.50",
    "2908": "15.24",
    "2910": "12.50",
    "2911": "13.19",
    "2912": "20.59",
    "2913": "-",
    "2915": "22.77",
    "3002": "8.44",
    "3003": "8.21",
    "3004": "-",
    "3005": "5.60",
    "3006": "10.15",
    "3008": "13.73",
    "3009": "2.24",
    "3010": "6.18",
    "3011": "-",
    "3013": "30.00",
    "3014": "10.74",
    "3015": "6.41",
    "3016": "95.00",
    "3017": "7.25",
    "3018": "-",
    "3019": "7.93",
    "3021": "6.15",
    "3022": "6.66",
    "3023": "5.18",
    "3024": "10.09",
    "3025": "14.68",
    "3026": "7.07",
    "3027": "6.51",
    "3028": "6.67",
    "3029": "14.59",
    "3030": "4.50",
    "3031": "11.43",
    "3032": "5.58",
    "3033": "7.11",
    "3034": "4.24",
    "3035": "11.56",
    "3036": "5.01",
    "3037": "5.10",
    "3038": "-",
    "3040": "5.37",
    "3041": "20.79",
    "3042": "9.07",
    "3043": "22.86",
    "3044": "6.23",
    "3045": "28.82",
    "3046": "4.65",
    "3047": "9.70",
    "3048": "6.10",
    "3050": "27.39",
    "3051": "-",
    "3052": "7.10",
    "3054": "25.73",
    "3055": "4.87",
    "3056": "-",
    "3057": "12.24",
    "3058": "-",
    "3059": "5.95",
    "3060": "8.24",
    "3061": "13.09",
    "3062": "16.11",
    "3063": "-",
    "3080": "5.07",
    "3090": "6.41",
    "3094": "12.90",
    "3130": "8.52",
    "3189": "5.03",
    "3231": "7.55",
    "3296": "6.50",
    "3305": "9.06",
    "3308": "10.07",
    "3311": "10.34",
    "3315": "4.59",
    "3356": "8.20",
    "3367": "5.54",
    "3376": "12.99",
    "3380": "7.90",
    "3383": "12.99",
    "3406": "-",
    "3419": "-",
    "3443": "27.96",
    "3450": "7.16",
    "3474": "-",
    "3481": "6.70",
    "3494": "15.82",
    "3501": "8.64",
    "3504": "11.43",
    "3514": "15.34",
    "3515": "8.80",
    "3518": "7.22",
    "3519": "13.65",
    "3532": "10.86",
    "3533": "6.84",
    "3534": "10.36",
    "3535": "7.55",
    "3536": "3.01",
    "3545": "14.00",
    "3557": "4.12",
    "3701": "-",
    "3702": "7.27",
    "4104": "7.85",
    "4106": "7.89",
    "4108": "-",
    "4119": "9.08",
    "4306": "7.40",
    "4414": "-",
    "4526": "5.72",
    "4532": "9.44",
    "4725": "3.72",
    "4904": "11.65",
    "4906": "11.81",
    "5203": "13.11",
    "5305": "5.96",
    "5388": "5.02",
    "5434": "5.71",
    "5469": "4.54",
    "5471": "8.54",
    "5484": "7.45",
    "5515": "7.36",
    "5522": "3.31",
    "5525": "4.06",
    "5531": "3.38",
    "5533": "2.72",
    "5534": "3.13",
    "5607": "18.20",
    "5608": "5.70",
    "5854": "8.82",
    "6005": "7.86",
    "6012": "-",
    "6112": "7.10",
    "6115": "7.24",
    "6116": "1.70",
    "6117": "11.11",
    "6119": "6.15",
    "6120": "-",
    "6128": "9.58",
    "6131": "8.75",
    "6133": "8.74",
    "6136": "5.02",
    "6139": "5.95",
    "6141": "5.35",
    "6142": "8.15",
    "6145": "-",
    "6153": "-",
    "6155": "9.29",
    "6165": "-",
    "6166": "5.88",
    "6168": "11.59",
    "6172": "-",
    "6176": "6.08",
    "6184": "10.36",
    "6189": "5.06",
    "6191": "4.85",
    "6192": "6.84",
    "6196": "7.22",
    "6197": "21.52",
    "6201": "6.44",
    "6202": "6.63",
    "6205": "4.82",
    "6206": "7.54",
    "6209": "9.67",
    "6213": "5.48",
    "6215": "8.27",
    "6216": "5.56",
    "6225": "14.09",
    "6235": "-",
    "6239": "5.52",
    "6255": "16.18",
    "6257": "5.54",
    "6269": "15.88",
    "6271": "8.74",
    "6277": "9.75",
    "6281": "7.38",
    "6282": "7.70",
    "6283": "7.23",
    "6285": "7.88",
    "6286": "12.82",
    "6289": "-",
    "6505": "9.27",
    "6605": "5.48",
    "8008": "7.97",
    "8016": "7.55",
    "8021": "4.82",
    "8033": "19.03",
    "8046": "6.37",
    "8070": "7.13",
    "8072": "9.65",
    "8078": "7.81",
    "8101": "-",
    "8105": "10.44",
    "8110": "5.04",
    "8112": "-",
    "8131": "6.29",
    "8163": "6.60",
    "8201": "10.53",
    "8249": "6.65",
    "8926": "14.44",
    "9902": "-",
    "9904": "6.54",
    "9905": "9.07",
    "9906": "7.69",
    "9907": "9.96",
    "9908": "22.19",
    "9910": "7.05",
    "9911": "6.84",
    "9912": "4.93",
    "9914": "7.44",
    "9917": "11.13",
    "9918": "17.10",
    "9919": "12.36",
    "9921": "11.69",
    "9922": "27.67",
    "9924": "106.82",
    "9925": "8.45",
    "9926": "9.42",
    "9927": "3.56",
    "9928": "-",
    "9929": "-",
    "9930": "8.04",
    "9931": "15.26",
    "9933": "7.98",
    "9934": "10.09",
    "9935": "23.95",
    "9937": "12.15",
    "9938": "8.99",
    "9939": "10.23",
    "9940": "9.28",
    "9941": "8.61",
    "9942": "6.85",
    "9943": "7.44",
    "9944": "1.41",
    "9945": "18.84",
    "9955": "12.71",
    "9958": "9.11"
}