{
    "1101": "24.47",
    "1102": "16.88",
    "1103": "-",
    "1104": "-",
    "1108": "-",
    "1109": "39.75",
    "1110": "-",
    "1201": "35.48",
    "1203": "5.59",
    "1210": "16.34",
    "1213": "54.00",
    "1215": "16.55",
    "1216": "28.38",
    "1217": "37.08",
    "1218": "-",
    "1219": "-",
    "1220": "-",
    "1225": "-",
    "1227": "14.05",
    "1229": "144.55",
    "1231": "16.08",
    "1232": "11.84",
    "1233": "21.33",
    "1234": "39.19",
    "1235": "-",
    "1236": "10.52",
    "1301": "22.03",
    "1303": "-",
    "1304": "-",
    "1305": "-",
    "1307": "9.77",
    "1308": "21.30",
    "1309": "-",
    "1310": "-",
    "1312": "-",
    "1313": "-",
    "1314": "-",
    "1315": "13.14",
    "1316": "-",
    "1319": "25.17",
    "1321": "-",
    "1323": "14.81",
    "1324": "20.32",
    "1325": "15.65",
    "1326": "-",
    "1402": "62.71",
    "1409": "-",
    "1410": "-",
    "1413": "-",
    "1414": "-",
    "1416": "-",
    "1417": "-",
    "1418": "-",
    "1419": "647.50",
    "1423": "-",
    "1432": "-",
    "1434": "12.96",
    "1435": "-",
    "1436": "-",
    "1437": "-",
    "1438": "-",
    "1439": "58.85",
    "1440": "-",
    "1441": "-",
    "1442": "8.62",
    "1443": "-",
    "1444": "-",
    "1445": "21.43",
    "1446": "-",
    "1447": "-",
    "1449": "-",
    "1451": "143.75",
    "1452": "-",
    "1453": "-",
    "1454": "85.71",
    "1455": "-",
    "1456": "-",
    "1457": "-",
    "1459": "-",
    "1460": "-",
    "1463": "-",
    "1464": "-",
    "1465": "13.84",
    "1466": "-",
    "1467": "-",
    "1468": "-",
    "1469": "-",
    "1470": "9.44",
    "1471": "-",
    "1472": "-",
    "1473": "19.96",
    "1474": "39.13",
    "1475": "-",
    "1476": "10.63",
    "1477": "24.89",
    "1503": "26.74",
    "1504": "17.78",
    "1506": "-",
    "1507": "11.80",
    "1512": "-",
    "1513": "18.79",
    "1514": "-",
    "1515": "-",
    "1516": "12.69",
    "1517": "9.42",
    "1519": "11.08",
    "1521": "22.06",
    "1522": "17.58",
    "1523": "14.51",
    "1524": "16.58",
    "1525": "11.66",
    "1526": "124.20",
    "1527": "7.91",
    "1528": "36.11",
    "1529": "-",
    "1530": "8.95",
    "1531": "9.61",
    "1532": "52.87",
    "1533": "-",
    "1535": "13.63",
    "1536": "-",
    "1537": "-",
    "1538": "6.08",
    "1539": "-",
    "1540": "7.13",
    "1541": "11.12",
    "1560": "-",
    "1583": "28.05",
    "1603": "19.33",
    "1604": "2.79",
    "1605": "-",
    "1608": "-",
    "1609": "-",
    "1611": "27.17",
    "1612": "100.00",
    "1613": "-",
    "1614": "40.74",
    "1615": "24.71",
    "1616": "-",
    "1617": "-",
    "1618": "-",
    "1701": "295.00",
    "1702": "-",
    "1704": "11.44",
    "1707": "16.07",
    "1708": "11.33",
    "1709": "11.48",
    "1710": "25.38",
    "1711": "270.00",
    "1712": "13.60",
    "1713": "297.50",
    "1714": "11.13",
    "1715": "26.57",
    "1716": "20.61",
    "1717": "10.38",
    "1718": "-",
    "1720": "16.37",
    "1721": "-",
    "1722": "62.28",
    "1723": "12.62",
    "1724": "17.92",
    "1725": "12.39",
    "1726": "15.58",
    "1727": "14.38",
    "1729": "58.49",
    "1730": "25.58",
    "1731": "36.50",
    "1732": "77.50",
    "1733": "18.80",
    "1734": "55.96",
    "1735": "-",
    "1736": "-",
    "1737": "-",
    "1773": "11.60",
    "1802": "103.86",
    "1805": "-",
    "1806": "26.67",
    "1808": "10.29",
    "1809": "23.04",
    "1810": "-",
    "1902": "-",
    "1903": "-",
    "1904": "48.41",
    "1905": "-",
    "1906": "14.05",
    "1907": "-",
    "1909": "-",
    "2002": "81.28",
    "2006": "48.47",
    "2007": "-",
    "2008": "-",
    "2009": "-",
    "2010": "-",
    "2012": "138.57",
    "2013": "14.36",
    "2014": "-",
    "2015": "25.40",
    "2017": "-",
    "2020": "-",
    "2022": "-",
    "2023": "60.45",
    "2024": "-",
    "2025": "-",
    "2027": "-",
    "2028": "-",
    "2029": "23.36",
    "2030": "-",
    "2031": "-",
    "2032": "-",
    "2033": "18.11",
    "2034": "-",
    "2038": "7.27",
    "2049": "8.44",
    "2059": "19.48",
    "2062": "11.77",
    "2101": "-",
    "2102": "-",
    "2103": "10.39",
    "2104": "41.73",
    "2105": "23.44",
    "2106": "29.31",
    "2107": "10.99",
    "2108": "14.46",
    "2109": "-",
    "2201": "-",
    "2204": "-",
    "2206": "-",
    "2207": "18.48",
    "2208": "28.66",
    "2227": "42.05",
    "2301": "20.08",
    "2302": "-",
    "2303": "-",
    "2305": "-",
    "2308": "20.24",
    "2311": "57.68",
    "2312": "-",
    "2313": "51.33",
    "2314": "22.46",
    "2315": "-",
    "2316": "-",
    "2317": "18.49",
    "2321": "-",
    "2323": "-",
    "2324": "10.22",
    "2325": "28.82",
    "2327": "-",
    "2328": "33.38",
    "2329": "-",
    "2330": "20.67",
    "2331": "46.61",
    "2332": "33.03",
    "2337": "12.16",
    "2338": "-",
    "2340": "77.50",
    "2341": "-",
    "2342": "-",
    "2344": "-",
    "2345": "15.79",
    "2347": "26.54",
    "2348": "-",
    "2349": "-",
    "2350": "-",
    "2351": "73.75",
    "2352": "-",
    "2353": "17.09",
    "2354": "14.14",
    "2355": "10.62",
    "2356": "8.60",
    "2357": "22.81",
    "2358": "11.90",
    "2359": "-",
    "2360": "20.78",
    "2361": "-",
    "2362": "40.87",
    "2363": "-",
    "2364": "-",
    "2365": "11.44",
    "2367": "-",
    "2368": "86.15",
    "2369": "35.28",
    "2371": "-",
    "2373": "17.23",
    "2374": "17.57",
    "2375": "-",
    "2376": "15.76",
    "2377": "19.91",
    "2379": "55.99",
    "2380": "12.86",
    "2382": "10.99",
    "2383": "29.77",
    "2384": "-",
    "2385": "15.42",
    "2387": "13.03",
    "2388": "-",
    "2390": "-",
    "2391": "40.29",
    "2392": "17.31",
    "2393": "27.40",
    "2395": "11.05",
    "2397": "11.65",
    "2399": "15.12",
    "2401": "-",
    "2402": "-",
    "2403": "12.52",
    "2404": "9.34",
    "2405": "388.00",
    "2406": "-",
    "2408": "-",
    "2409": "-",
    "2412": "14.15",
    "2413": "41.25",
    "2414": "18.41",
    "2415": "65.31",
    "2417": "10.96",
    "2419": "20.41",
    "2420": "12.20",
    "2421": "52.64",
    "2423": "13.00",
    "2424": "-",
    "2425": "-",
    "2426": "-",
    "2427": "642.00",
    "2428": "13.67",
    "2429": "-",
    "2430": "19.39",
    "2431": "-",
    "2433": "7.26",
    "2434": "-",
    "2436": "92.50",
    "2437": "15.25",
    "2438": "-",
    "2439": "10.86",
    "2440": "-",
    "2441": "13.10",
    "2442": "-",
    "2443": "-",
    "2444": "-",
    "2446": "-",
    "2448": "-",
    "2449": "-",
    "2450": "9.54",
    "2451": "14.84",
    "2452": "14.96",
    "2453": "32.32",
    "2454": "22.88",
    "2455": "-",
    "2456": "28.07",
    "2457": "14.34",
    "2458": "148.61",
    "2459": "11.31",
    "2460": "12.27",
    "2461": "28.80",
    "2462": "11.10",
    "2463": "12.19",
    "2464": "8.75",
    "2465": "-",
    "2466": "-",
    "2467": "9.24",
    "2468": "9.91",
    "2471": "-",
    "2472": "21.83",
    "2473": "15.73",
    "2474": "13.29",
    "2475": "-",
    "2476": "16.05",
    "2477": "-",
    "2478": "21.00",
    "2480": "8.89",
    "2481": "-",
    "2482": "46.05",
    "2483": "46.30",
    "2484": "23.92",
    "2485": "13.51",
    "2486": "20.19",
    "2488": "8.16",
    "2489": "13.22",
    "2491": "-",
    "2492": "-",
    "2493": "155.50",
    "2495": "10.77",
    "2496": "-",
    "2497": "-",
    "2498": "12.56",
    "2499": "338.33",
    "2501": "77.78",
    "2504": "42.62",
    "2505": "-",
    "2506": "-",
    "2509": "15.30",
    "2511": "-",
    "2514": "-",
    "2515": "-",
    "2516": "9.64",
    "2520": "21.76",
    "2524": "17.39",
    "2526": "56.19",
    "2527": "101.94",
    "2528": "-",
    "2530": "-",
    "2534": "-",
    "2535": "22.03",
    "2536": "7.34",
    "2537": "-",
    "2538": "13.18",
    "2539": "10.30",
    "2540": "1.07",
    "2542": "14.13",
    "2543": "21.00",
    "2545": "29.81",
    "2546": "15.84",
    "2547": "-",
    "2548": "7.01",
    "2601": "5.54",
    "2603": "-",
    "2605": "7.44",
    "2606": "5.93",
    "2607": "35.80",
    "2608": "24.78",
    "2609": "-",
    "2610": "-",
    "2611": "85.00",
    "2612": "5.25",
    "2613": "11.13",
    "2614": "-",
    "2615": "-",
    "2616": "12.75",
    "2617": "7.16",
    "2618": "-",
    "2701": "30.64",
    "2702": "68.60",
    "2704": "60.39",
    "2705": "-",
    "2706": "23.64",
    "2707": "47.81",
    "2801": "16.04",
    "2809": "-",
    "2812": "-",
    "2816": "-",
    "2820": "11.03",
    "2823": "5.52",
    "2832": "-",
    "2833": "-",
    "2834": "-",
    "2836": "-",
    "2837": "-",
    "2838": "-",
    "2841": "90.83",
    "2845": "-",
    "2847": "-",
    "2849": "-",
    "2850": "10.65",
    "2851": "17.98",
    "2852": "-",
    "2854": "-",
    "2855": "-",
    "2856": "-",
    "2880": "16.25",
    "2881": "27.14",
    "2882": "37.89",
    "2883": "-",
    "2884": "49.78",
    "2885": "124.21",
    "2886": "58.97",
    "2887": "-",
    "2888": "-",
    "2889": "-",
    "2890": "-",
    "2891": "14.31",
    "2892": "24.34",
    "2901": "90.00",
    "2903": "122.59",
    "2904": "10.47",
    "2905": "94.67",
    "2906": "104.38",
    "2908": "34.67",
    "2910": "29.24",
    "2911": "26.61",
    "2912": "22.76",
    "2913": "568.33",
    "2915": "104.58",
    "3002": "12.41",
    "3003": "21.54",
    "3004": "-",
    "3005": "14.51",
    "3006": "-",
    "3008": "17.64",
    "3009": "-",
    "3010": "15.14",
    "3011": "-",
    "3013": "11.17",
    "3014": "32.39",
    "3015": "9.12",
    "3016": "-",
    "3017": "13.82",
    "3018": "39.67",
    "3019": "20.43",
    "3021": "-",
    "3022": "12.67",
    "3023": "100.31",
    "3024": "-",
    "3025": "21.61",
    "3026": "16.10",
    "3027": "1,230.00",
    "3028": "16.19",
    "3029": "23.31",
    "3030": "12.56",
    "3031": "29.88",
    "3032": "11.11",
    "3033": "12.52",
    "3034": "18.07",
    "3035": "38.25",
    "3036": "28.37",
    "3037": "24.80",
    "3038": "-",
    "3040": "25.00",
    "3041": "60.73",
    "3042": "13.32",
    "3043": "-",
    "3044": "14.47",
    "3045": "13.21",
    "3046": "52.50",
    "3047": "17.13",
    "3048": "-",
    "3049": "-",
    "3050": "-",
    "3051": "-",
    "3052": "10.08",
    "3054": "32.09",
    "3055": "11.06",
    "3056": "-",
    "3057": "14.79",
    "3058": "15.96",
    "3059": "11.44",
    "3060": "8.22",
    "3061": "-",
    "3062": "36.75",
    "3063": "-",
    "3080": "720.00",
    "3090": "9.64",
    "3094": "44.00",
    "3130": "12.05",
    "3189": "17.16",
    "3209": "9.43",
    "3231": "16.43",
    "3296": "17.09",
    "3305": "21.96",
    "3308": "13.18",
    "3311": "13.01",
    "3315": "9.03",
    "3356": "11.81",
    "3367": "10.13",
    "3376": "19.40",
    "3380": "11.32",
    "3383": "30.18",
    "3406": "-",
    "3419": "-",
    "3443": "34.62",
    "3450": "26.74",
    "3474": "-",
    "3481": "-",
    "3494": "10.05",
    "3501": "15.25",
    "3504": "29.40",
    "3514": "10.48",
    "3515": "23.97",
    "3518": "15.97",
    "3519": "8.52",
    "3532": "61.46",
    "3533": "16.40",
    "3534": "20.13",
    "3535": "6.34",
    "3536": "-",
    "3545": "30.87",
    "3557": "97.50",
    "3559": "10.00",
    "3561": "8.60",
    "3576": "8.32",
    "3593": "11.60",
    "3596": "11.41",
    "3605": "15.65",
    "3614": "52.30",
    "3622": "39.27",
    "3701": "-",
    "3702": "18.66",
    "4104": "28.44",
    "4106": "13.68",
    "4108": "-",
    "4119": "18.50",
    "4306": "8.84",
    "4414": "-",
    "4526": "8.98",
    "4532": "-",
    "4725": "-",
    "4904": "12.53",
    "4906": "12.76",
    "5203": "14.99",
    "5305": "-",
    "5388": "11.40",
    "5434": "20.84",
    "5469": "20.39",
    "5471": "15.82",
    "5484": "13.56",
    "5515": "10.58",
    "5522": "12.26",
    "5525": "12.53",
    "5531": "20.89",
    "5533": "13.88",
    "5534": "7.95",
    "5607": "-",
    "5608": "5.02",
    "5854": "16.42",
    "6005": "-",
    "6012": "-",
    "6108": "14.24",
    "6112": "15.14",
    "6115": "11.18",
    "6116": "-",
    "6117": "12.38",
    "6119": "30.14",
    "6120": "-",
    "6128": "13.88",
    "6131": "9.50",
    "6133": "-",
    "6136": "9.23",
    "6139": "11.48",
    "6141": "9.32",
    "6142": "13.82",
    "6145": "-",
    "6153": "32.76",
    "6155": "16.84",
    "6164": "21.28",
    "6165": "-",
    "6166": "12.83",
    "6168": "34.25",
    "6172": "-",
    "6176": "19.10",
    "6184": "12.75",
    "6189": "10.45",
    "6191": "24.61",
    "6192": "9.10",
    "6196": "10.07",
    "6197": "-",
    "6201": "8.83",
    "6202": "15.37",
    "6205": "12.06",
    "6206": "13.07",
    "6209": "-",
    "6213": "15.51",
    "6215": "30.00",
    "6216": "13.81",
    "6225": "-",
    "6226": "76.94",
    "6235": "-",
    "6239": "9.57",
    "6251": "12.88",
    "6255": "-",
    "6257": "19.45",
    "6269": "14.95",
    "6271": "21.08",
    "6277": "15.10",
    "6281": "11.13",
    "6282": "9.84",
    "6283": "35.41",
    "6285": "12.97",
    "6286": "28.85",
    "6289": "-",
    "6505": "91.07",
    "6605": "11.15",
    "8008": "21.44",
    "8016": "17.94",
    "8021": "22.17",
    "8033": "90.00",
    "8046": "13.04",
    "8070": "90.70",
    "8072": "9.01",
    "8078": "17.74",
    "8081": "21.88",
    "8101": "-",
    "8105": "-",
    "8110": "44.10",
    "8112": "-",
    "8131": "28.73",
    "8163": "30.60",
    "8201": "58.00",
    "8249": "-",
    "8374": "12.90",
    "8926": "9.17",
    "8940": "26.25",
    "9902": "-",
    "9904": "18.56",
    "9905": "21.21",
    "9906": "-",
    "9907": "20.50",
    "9908": "22.64",
    "9910": "10.90",
    "9911": "55.40",
    "9912": "-",
    "9914": "9.98",
    "9917": "17.55",
    "9918": "15.69",
    "9919": "21.92",
    "9921": "10.35",
    "9922": "-",
    "9924": "19.94",
    "9925": "11.82",
    "9926": "11.92",
    "9927": "-",
    "9928": "-",
    "9929": "-",
    "9930": "12.05",
    "9931": "13.31",
    "9933": "13.43",
    "9934": "29.88",
    "9935": "-",
    "9937": "19.58",
    "9938": "55.81",
    "9939": "13.54",
    "9940": "30.51",
    "9941": "13.36",
    "9942": "9.63",
    "9943": "10.42",
    "9944": "18.97",
    "9945": "87.79",
    "9955": "38.89",
    "9958": "143.33"
}