{
    "1101": "15.48",
    "1102": "13.56",
    "1103": "-",
    "1104": "10.44",
    "1108": "8.92",
    "1110": "91.76",
    "1201": "-",
    "1203": "15.68",
    "1210": "18.53",
    "1213": "39.61",
    "1215": "7.95",
    "1216": "24.83",
    "1217": "-",
    "1218": "81.92",
    "1219": "45.00",
    "1220": "41.21",
    "1225": "102.39",
    "1227": "22.46",
    "1229": "10.67",
    "1231": "13.08",
    "1232": "12.33",
    "1233": "18.25",
    "1234": "23.08",
    "1235": "-",
    "1236": "23.96",
    "1262": "11.63",
    "1301": "22.72",
    "1303": "15.90",
    "1304": "17.13",
    "1305": "16.16",
    "1307": "16.98",
    "1308": "16.58",
    "1309": "-",
    "1310": "44.22",
    "1312": "11.62",
    "1313": "26.76",
    "1314": "13.54",
    "1315": "17.92",
    "1316": "-",
    "1319": "25.90",
    "1321": "-",
    "1323": "9.69",
    "1324": "21.70",
    "1325": "26.51",
    "1326": "29.34",
    "1337": "9.33",
    "1338": "13.41",
    "1339": "15.83",
    "1340": "6.84",
    "1402": "14.36",
    "1409": "20.70",
    "1410": "13.92",
    "1413": "-",
    "1414": "-",
    "1416": "9.44",
    "1417": "-",
    "1418": "-",
    "1419": "-",
    "1423": "-",
    "1432": "-",
    "1434": "15.71",
    "1435": "-",
    "1436": "32.90",
    "1437": "33.92",
    "1438": "28.76",
    "1439": "218.33",
    "1440": "31.15",
    "1441": "-",
    "1442": "7.94",
    "1443": "-",
    "1444": "24.08",
    "1445": "28.06",
    "1446": "-",
    "1447": "36.88",
    "1449": "-",
    "1451": "22.97",
    "1452": "10.59",
    "1453": "16.30",
    "1454": "13.48",
    "1455": "24.29",
    "1456": "-",
    "1457": "8.32",
    "1459": "11.79",
    "1460": "18.98",
    "1463": "24.77",
    "1464": "7.80",
    "1465": "16.48",
    "1466": "145.00",
    "1467": "28.23",
    "1468": "-",
    "1469": "315.00",
    "1470": "30.16",
    "1471": "-",
    "1472": "-",
    "1473": "28.82",
    "1474": "14.86",
    "1475": "-",
    "1476": "34.91",
    "1477": "23.99",
    "1503": "16.33",
    "1504": "16.35",
    "1506": "74.09",
    "1507": "10.45",
    "1512": "-",
    "1513": "11.19",
    "1514": "12.17",
    "1515": "15.43",
    "1516": "5.38",
    "1517": "14.42",
    "1519": "13.08",
    "1521": "14.59",
    "1522": "12.56",
    "1524": "-",
    "1525": "16.57",
    "1526": "12.79",
    "1527": "11.81",
    "1528": "-",
    "1529": "-",
    "1530": "11.34",
    "1531": "21.19",
    "1532": "13.56",
    "1533": "31.09",
    "1535": "11.54",
    "1536": "30.42",
    "1537": "14.09",
    "1538": "-",
    "1539": "15.30",
    "1540": "8.19",
    "1541": "24.71",
    "1558": "10.41",
    "1560": "13.01",
    "1568": "15.75",
    "1582": "8.96",
    "1583": "10.09",
    "1589": "23.98",
    "1590": "19.32",
    "1592": "19.90",
    "1603": "10.54",
    "1604": "10.00",
    "1605": "11.72",
    "1608": "-",
    "1609": "-",
    "1611": "-",
    "1612": "19.80",
    "1613": "-",
    "1614": "26.53",
    "1615": "67.33",
    "1616": "4.38",
    "1617": "35.70",
    "1618": "-",
    "1626": "191.15",
    "1701": "14.36",
    "1702": "16.62",
    "1704": "54.41",
    "1707": "23.24",
    "1708": "8.17",
    "1709": "18.97",
    "1710": "47.88",
    "1711": "23.40",
    "1712": "15.43",
    "1713": "27.16",
    "1714": "-",
    "1715": "10.74",
    "1717": "12.74",
    "1718": "6.60",
    "1720": "18.05",
    "1721": "49.32",
    "1722": "13.41",
    "1723": "17.16",
    "1724": "19.11",
    "1725": "14.75",
    "1726": "11.49",
    "1727": "15.71",
    "1729": "-",
    "1730": "13.20",
    "1731": "20.36",
    "1732": "-",
    "1733": "18.55",
    "1734": "-",
    "1735": "9.20",
    "1736": "8.87",
    "1737": "21.47",
    "1762": "13.59",
    "1773": "10.97",
    "1783": "-",
    "1786": "-",
    "1789": "72.45",
    "1802": "-",
    "1805": "-",
    "1806": "-",
    "1808": "8.73",
    "1809": "14.93",
    "1810": "36.35",
    "1817": "12.22",
    "1902": "26.46",
    "1903": "-",
    "1904": "8.53",
    "1906": "25.94",
    "1907": "17.34",
    "1909": "10.04",
    "2002": "15.04",
    "2006": "19.69",
    "2007": "-",
    "2008": "-",
    "2009": "-",
    "2010": "13.54",
    "2012": "24.21",
    "2013": "17.30",
    "2014": "-",
    "2015": "11.85",
    "2017": "-",
    "2020": "30.33",
    "2022": "-",
    "2023": "15.33",
    "2024": "11.15",
    "2025": "-",
    "2027": "11.67",
    "2028": "-",
    "2029": "12.57",
    "2030": "13.29",
    "2031": "19.03",
    "2032": "43.29",
    "2033": "-",
    "2034": "10.77",
    "2038": "-",
    "2049": "18.98",
    "2059": "22.13",
    "2062": "11.36",
    "2101": "63.30",
    "2102": "17.71",
    "2103": "17.50",
    "2104": "5.36",
    "2105": "12.49",
    "2106": "13.00",
    "2107": "5.85",
    "2108": "16.57",
    "2109": "5.75",
    "2114": "11.91",
    "2115": "14.53",
    "2201": "22.60",
    "2204": "11.13",
    "2206": "-",
    "2207": "21.50",
    "2208": "19.42",
    "2227": "13.26",
    "2228": "23.92",
    "2231": "29.18",
    "2236": "9.34",
    "2301": "12.79",
    "2302": "7.90",
    "2303": "9.65",
    "2305": "8.02",
    "2308": "21.58",
    "2311": "12.50",
    "2312": "7.26",
    "2313": "11.58",
    "2314": "-",
    "2316": "1.73",
    "2317": "8.98",
    "2321": "-",
    "2323": "-",
    "2324": "8.66",
    "2325": "10.63",
    "2327": "9.78",
    "2328": "73.33",
    "2329": "10.34",
    "2330": "11.45",
    "2331": "9.72",
    "2332": "-",
    "2337": "-",
    "2338": "-",
    "2340": "11.08",
    "2342": "-",
    "2344": "7.60",
    "2345": "14.87",
    "2347": "10.13",
    "2348": "58.06",
    "2349": "-",
    "2351": "7.51",
    "2352": "7.04",
    "2353": "29.49",
    "2354": "8.90",
    "2355": "10.63",
    "2356": "10.28",
    "2357": "11.80",
    "2358": "-",
    "2359": "7.74",
    "2360": "17.73",
    "2361": "-",
    "2362": "11.62",
    "2363": "-",
    "2364": "-",
    "2365": "17.64",
    "2367": "11.08",
    "2368": "7.04",
    "2369": "100.00",
    "2371": "-",
    "2373": "14.66",
    "2374": "12.95",
    "2375": "16.05",
    "2376": "10.74",
    "2377": "9.98",
    "2379": "11.08",
    "2380": "-",
    "2382": "12.60",
    "2383": "10.75",
    "2385": "13.46",
    "2387": "9.02",
    "2388": "-",
    "2390": "-",
    "2392": "13.85",
    "2393": "10.12",
    "2395": "29.03",
    "2397": "12.24",
    "2399": "-",
    "2401": "8.91",
    "2402": "16.18",
    "2404": "10.56",
    "2405": "-",
    "2406": "-",
    "2408": "3.79",
    "2409": "4.27",
    "2412": "19.72",
    "2413": "10.25",
    "2414": "11.25",
    "2415": "8.66",
    "2417": "-",
    "2419": "28.13",
    "2420": "9.43",
    "2421": "14.02",
    "2423": "12.44",
    "2424": "-",
    "2425": "10.14",
    "2426": "10.78",
    "2427": "324.00",
    "2428": "8.87",
    "2429": "-",
    "2430": "1,007.50",
    "2431": "13.78",
    "2433": "12.67",
    "2434": "-",
    "2436": "25.58",
    "2437": "10.19",
    "2438": "-",
    "2439": "15.51",
    "2440": "62.77",
    "2441": "8.28",
    "2442": "8.20",
    "2443": "-",
    "2444": "-",
    "2448": "12.10",
    "2449": "9.95",
    "2450": "19.12",
    "2451": "11.84",
    "2453": "21.64",
    "2454": "11.54",
    "2455": "16.27",
    "2456": "12.20",
    "2457": "-",
    "2458": "13.58",
    "2459": "8.71",
    "2460": "107.11",
    "2461": "23.15",
    "2462": "14.95",
    "2464": "11.61",
    "2465": "14.65",
    "2466": "-",
    "2467": "17.74",
    "2468": "13.46",
    "2471": "12.39",
    "2474": "11.75",
    "2475": "-",
    "2476": "11.95",
    "2477": "-",
    "2478": "19.53",
    "2480": "12.18",
    "2481": "30.95",
    "2482": "31.20",
    "2483": "10.34",
    "2484": "10.90",
    "2485": "20.54",
    "2486": "195.00",
    "2488": "12.90",
    "2489": "26.97",
    "2491": "-",
    "2492": "10.78",
    "2493": "8.72",
    "2495": "16.18",
    "2496": "-",
    "2497": "12.31",
    "2498": "-",
    "2499": "29.25",
    "2501": "5.16",
    "2504": "19.48",
    "2505": "29.05",
    "2506": "11.40",
    "2509": "-",
    "2511": "6.80",
    "2514": "17.02",
    "2515": "4.94",
    "2516": "10.63",
    "2520": "6.38",
    "2524": "8.26",
    "2527": "3.38",
    "2528": "332.67",
    "2530": "-",
    "2534": "24.33",
    "2535": "13.41",
    "2536": "4.37",
    "2537": "11.95",
    "2538": "3.98",
    "2539": "4.43",
    "2540": "55.56",
    "2542": "4.39",
    "2543": "7.09",
    "2545": "8.08",
    "2546": "15.68",
    "2547": "-",
    "2548": "4.49",
    "2597": "5.48",
    "2601": "-",
    "2603": "12.63",
    "2605": "13.42",
    "2606": "25.33",
    "2607": "16.83",
    "2608": "14.98",
    "2609": "14.85",
    "2610": "10.69",
    "2611": "13.58",
    "2612": "17.60",
    "2613": "14.23",
    "2614": "-",
    "2615": "7.46",
    "2616": "10.66",
    "2617": "31.02",
    "2618": "23.64",
    "2634": "19.55",
    "2637": "9.00",
    "2642": "17.98",
    "2701": "17.32",
    "2702": "20.14",
    "2704": "23.61",
    "2705": "8.78",
    "2706": "17.26",
    "2707": "21.14",
    "2712": "24.49",
    "2722": "25.11",
    "2723": "38.99",
    "2727": "35.48",
    "2731": "20.36",
    "2801": "12.50",
    "2809": "6.64",
    "2812": "7.63",
    "2816": "8.27",
    "2820": "10.27",
    "2823": "8.38",
    "2832": "7.25",
    "2834": "8.51",
    "2836": "10.98",
    "2838": "8.12",
    "2841": "1.29",
    "2845": "7.65",
    "2847": "12.90",
    "2849": "9.42",
    "2850": "6.31",
    "2851": "9.69",
    "2852": "7.54",
    "2855": "12.73",
    "2856": "13.49",
    "2867": "6.12",
    "2880": "10.36",
    "2881": "7.32",
    "2882": "9.79",
    "2883": "12.12",
    "2884": "12.47",
    "2885": "11.10",
    "2886": "9.87",
    "2887": "128.00",
    "2888": "7.73",
    "2889": "14.29",
    "2890": "8.35",
    "2891": "10.08",
    "2892": "10.53",
    "2901": "52.94",
    "2903": "23.97",
    "2904": "11.12",
    "2905": "6.29",
    "2906": "8.30",
    "2908": "14.05",
    "2910": "50.87",
    "2911": "-",
    "2912": "27.69",
    "2913": "11.76",
    "2915": "5.36",
    "2923": "10.59",
    "2929": "10.07",
    "3002": "19.65",
    "3003": "17.63",
    "3004": "-",
    "3005": "9.52",
    "3006": "8.53",
    "3008": "14.76",
    "3010": "8.92",
    "3011": "-",
    "3013": "28.90",
    "3014": "15.62",
    "3016": "-",
    "3017": "11.24",
    "3018": "40.73",
    "3019": "-",
    "3021": "19.67",
    "3022": "9.43",
    "3023": "13.39",
    "3024": "-",
    "3025": "138.83",
    "3026": "10.50",
    "3027": "34.87",
    "3028": "9.85",
    "3029": "14.75",
    "3030": "9.23",
    "3031": "31.32",
    "3032": "11.90",
    "3033": "11.82",
    "3034": "9.55",
    "3035": "30.98",
    "3036": "7.35",
    "3037": "-",
    "3038": "8.92",
    "3040": "3.92",
    "3041": "395.00",
    "3042": "12.15",
    "3043": "-",
    "3044": "10.10",
    "3045": "19.29",
    "3046": "-",
    "3047": "22.50",
    "3048": "7.76",
    "3049": "38.21",
    "3050": "377.50",
    "3051": "3.13",
    "3052": "15.44",
    "3054": "-",
    "3055": "9.46",
    "3056": "5.29",
    "3057": "10.87",
    "3058": "34.52",
    "3059": "75.26",
    "3060": "14.01",
    "3062": "13.36",
    "3090": "10.30",
    "3094": "27.42",
    "3130": "14.40",
    "3149": "-",
    "3164": "-",
    "3167": "7.78",
    "3189": "11.19",
    "3209": "8.35",
    "3229": "99.50",
    "3231": "15.09",
    "3257": "10.13",
    "3266": "-",
    "3296": "171.50",
    "3305": "15.71",
    "3308": "11.12",
    "3311": "-",
    "3312": "15.91",
    "3315": "16.22",
    "3338": "14.55",
    "3356": "14.65",
    "3376": "12.37",
    "3380": "17.89",
    "3383": "-",
    "3406": "-",
    "3413": "10.94",
    "3416": "13.62",
    "3419": "-",
    "3432": "32.44",
    "3437": "12.35",
    "3443": "23.47",
    "3450": "12.26",
    "3454": "14.19",
    "3474": "3.69",
    "3481": "3.44",
    "3494": "49.56",
    "3501": "9.09",
    "3504": "23.45",
    "3514": "-",
    "3515": "11.93",
    "3518": "-",
    "3519": "-",
    "3532": "23.15",
    "3533": "11.19",
    "3535": "-",
    "3536": "-",
    "3545": "-",
    "3550": "12.26",
    "3557": "-",
    "3559": "9.21",
    "3561": "-",
    "3573": "-",
    "3576": "-",
    "3579": "-",
    "3583": "23.30",
    "3584": "-",
    "3588": "14.63",
    "3591": "-",
    "3593": "-",
    "3596": "12.52",
    "3598": "8.13",
    "3605": "13.74",
    "3607": "7.71",
    "3617": "13.05",
    "3622": "-",
    "3645": "12.32",
    "3653": "17.05",
    "3661": "47.79",
    "3665": "19.36",
    "3669": "-",
    "3673": "-",
    "3679": "14.33",
    "3682": "-",
    "3686": "-",
    "3694": "-",
    "3698": "15.92",
    "3701": "-",
    "3702": "10.41",
    "3703": "-",
    "3704": "-",
    "3705": "17.07",
    "3706": "12.33",
    "4104": "17.11",
    "4106": "18.71",
    "4108": "-",
    "4119": "17.79",
    "4133": "28.05",
    "4137": "25.83",
    "4141": "-",
    "4142": "-",
    "4144": "13.38",
    "4164": "37.64",
    "4306": "20.92",
    "4414": "-",
    "4426": "28.04",
    "4526": "15.89",
    "4532": "10.81",
    "4536": "19.23",
    "4551": "17.58",
    "4557": "12.71",
    "4720": "10.61",
    "4722": "11.33",
    "4725": "-",
    "4733": "23.44",
    "4737": "34.47",
    "4746": "25.04",
    "4755": "13.27",
    "4904": "21.00",
    "4906": "68.96",
    "4912": "16.02",
    "4915": "12.06",
    "4916": "-",
    "4919": "14.69",
    "4927": "13.45",
    "4930": "2.93",
    "4934": "-",
    "4935": "11.83",
    "4938": "9.74",
    "4942": "30.58",
    "4952": "10.90",
    "4956": "15.30",
    "4958": "9.35",
    "4960": "5.89",
    "4976": "-",
    "4977": "12.61",
    "4984": "14.63",
    "4994": "47.92",
    "4999": "7.55",
    "5007": "19.18",
    "5203": "11.56",
    "5215": "8.61",
    "5225": "12.11",
    "5234": "9.57",
    "5243": "11.71",
    "5259": "-",
    "5264": "10.68",
    "5269": "67.53",
    "5285": "11.84",
    "5288": "11.83",
    "5305": "9.94",
    "5388": "18.16",
    "5434": "8.78",
    "5469": "7.57",
    "5471": "14.60",
    "5484": "-",
    "5515": "53.16",
    "5519": "5.00",
    "5521": "41.85",
    "5522": "4.22",
    "5525": "4.22",
    "5531": "27.44",
    "5533": "5.36",
    "5534": "6.29",
    "5538": "9.98",
    "5607": "14.58",
    "5608": "39.41",
    "5706": "13.36",
    "5871": "9.70",
    "5880": "13.94",
    "5906": "-",
    "5907": "7.38",
    "6005": "12.18",
    "6108": "46.21",
    "6112": "11.05",
    "6115": "11.98",
    "6116": "-",
    "6117": "-",
    "6120": "6.59",
    "6128": "11.53",
    "6131": "-",
    "6133": "32.27",
    "6136": "11.77",
    "6139": "24.05",
    "6141": "-",
    "6142": "-",
    "6145": "15.40",
    "6152": "-",
    "6153": "49.54",
    "6155": "12.78",
    "6164": "12.20",
    "6165": "-",
    "6166": "26.43",
    "6168": "-",
    "6172": "6.31",
    "6176": "17.58",
    "6177": "4.08",
    "6183": "18.78",
    "6184": "15.44",
    "6189": "9.50",
    "6191": "-",
    "6192": "9.55",
    "6196": "11.25",
    "6197": "19.97",
    "6201": "11.60",
    "6202": "13.84",
    "6205": "8.76",
    "6206": "14.00",
    "6209": "-",
    "6213": "16.46",
    "6214": "20.56",
    "6215": "14.70",
    "6216": "10.04",
    "6224": "12.19",
    "6225": "-",
    "6226": "-",
    "6230": "11.96",
    "6235": "-",
    "6239": "14.18",
    "6243": "-",
    "6251": "-",
    "6257": "8.75",
    "6269": "9.69",
    "6271": "11.30",
    "6277": "11.48",
    "6278": "7.85",
    "6281": "12.31",
    "6282": "15.30",
    "6283": "-",
    "6285": "16.08",
    "6286": "18.23",
    "6289": "-",
    "6405": "8.28",
    "6409": "23.54",
    "6412": "12.27",
    "6414": "32.77",
    "6415": "26.05",
    "6422": "8.77",
    "6431": "8.70",
    "6442": "11.84",
    "6443": "-",
    "6449": "10.65",
    "6451": "12.04",
    "6452": "23.08",
    "6456": "27.84",
    "6504": "24.48",
    "6505": "39.27",
    "6605": "11.96",
    "6702": "-",
    "8011": "57.67",
    "8016": "14.72",
    "8021": "11.43",
    "8033": "-",
    "8039": "10.33",
    "8046": "16.57",
    "8070": "5.99",
    "8072": "13.43",
    "8081": "10.07",
    "8101": "154.83",
    "8103": "6.06",
    "8105": "114.09",
    "8110": "10.75",
    "8112": "12.69",
    "8114": "21.25",
    "8131": "8.97",
    "8150": "9.31",
    "8163": "27.31",
    "8201": "-",
    "8210": "10.74",
    "8213": "6.72",
    "8215": "10.22",
    "8222": "28.89",
    "8249": "9.38",
    "8261": "12.55",
    "8271": "7.94",
    "8341": "27.70",
    "8374": "-",
    "8404": "12.93",
    "8411": "28.68",
    "8422": "16.02",
    "8427": "10.61",
    "8429": "7.65",
    "8443": "15.60",
    "8454": "20.69",
    "8463": "9.22",
    "8926": "10.33",
    "8940": "-",
    "8996": "28.04",
    "9802": "33.46",
    "9902": "99.58",
    "9904": "12.88",
    "9905": "11.23",
    "9906": "93.64",
    "9907": "26.25",
    "9908": "19.13",
    "9910": "30.38",
    "9911": "9.89",
    "9912": "-",
    "9914": "18.62",
    "9917": "20.54",
    "9918": "28.44",
    "9919": "42.50",
    "9921": "24.01",
    "9924": "14.04",
    "9925": "13.56",
    "9926": "24.48",
    "9927": "9.47",
    "9928": "-",
    "9929": "-",
    "9930": "14.74",
    "9931": "18.56",
    "9933": "15.47",
    "9934": "14.63",
    "9935": "-",
    "9937": "24.33",
    "9938": "23.21",
    "9939": "14.72",
    "9940": "20.96",
    "9941": "12.30",
    "9942": "14.14",
    "9943": "8.21",
    "9944": "29.44",
    "9945": "5.61",
    "9946": "33.14",
    "9955": "-",
    "9958": "123.75"
}